{
  "users":
  [
    "mauricio.jackson@mercadolibre.com",
    "diego.romero@mercadolibre.com",
    "carolina.alvarez@mercadolibre.com",
    "martin.ciruzzi@mercadolibre.com"
  ],
  "process_name": "recommendations_btr",
  "cron": "15 19 * * *",
  "extract":
  {
    "operation": "append",
    "columns":
    [
      {
        "name": "ds",
        "type": "DATE",
        "format": "yyyy-MM-dd"
      },
      {
        "name": "platform",
        "type": "UNICODE_STRING"
      },
      {
        "name": "site_id",
        "type": "UNICODE_STRING"
      },
      {
        "name": "backend",
        "type": "UNICODE_STRING"
      },
      {
        "name": "client",
        "type": "UNICODE_STRING"
      },
      {
        "name": "prints",
        "type": "INTEGER"
      },
      {
        "name": "orders",
        "type": "INTEGER"
      },
      {
        "name": "GMV",
        "type": "DOUBLE"
      }
    ],
    "sql": {
      "script": "melidata/recommendations-btr.sql",
      "parameters": [
        {
          "name": "param01",
          "value": "2016-12-19",
          "format": "yyyy-MM-dd"
        },
        {
          "name": "param02",
          "value": "2016-12-26",
          "format": "yyyy-MM-dd"
        },
        {
          "name": "param03",
          "value": "2016-12-28",
          "format": "yyyy-MM-dd"
        }
      ]
    }
  }
}